{
  "generatedAt": "2026-03-17T07:11:28.672Z",
  "runId": "mmu9xhuh",
  "origin": "http://web:3000",
  "appBaseUrl": "http://web:3000/app/",
  "owner": {
    "email": "owner.e2e@shadowob.local",
    "password": "ShadowE2E123!",
    "displayName": "Ava Owner"
  },
  "viewer": {
    "email": "viewer.mmu9xhuh@shadowob.local",
    "password": "ShadowE2E123!",
    "displayName": "Ben Viewer"
  },
  "server": {
    "id": "09507c2a-6ed9-45a3-a496-53cb101c784b",
    "slug": "e2e-studio",
    "name": "E2E Studio",
    "inviteCode": "EreWwPnm"
  },
  "channels": {
    "generalId": "d7e0a3d1-35f3-4f29-8b14-91a2f3bffc44",
    "announcementsId": "d16a0178-4dcd-4e94-a098-d071f067ed71"
  },
  "shop": {
    "categoryId": "902ad30c-121e-47aa-8086-6eb0a5641dc7",
    "categoryName": "Studio Kits",
    "productNames": ["Focus Sprint Bundle", "Buddy Ops Pass"]
  },
  "apps": {
    "names": ["Launchpad", "Ops Console"]
  }
}
